{"games":[{"url":"https://www.chess.com/game/daily/203173850","pgn":"[Event \"Let's Play!\"]\n[Site \"Chess.com\"]\n[Date \"2018.08.30\"]\n[Round \"-\"]\n[White \"OzzyTor\"]\n[Black \"okiedoak\"]\n[Result \"1-0\"]\n[CurrentPosition \"Bk6/1Q6/8/1p4np/p7/P7/1PP2PPP/2KR4 b - - 2 34\"]\n[Timezone \"UTC\"]\n[ECO \"B06\"]\n[ECOUrl \"https://www.chess.com/openings/Modern-Defense-with-1-e4-2.Bc4\"]\n[UTCDate \"2018.08.30\"]\n[UTCTime \"23:43:03\"]\n[WhiteElo \"1433\"]\n[BlackElo \"1185\"]\n[TimeControl \"1/259200\"]\n[Termination \"OzzyTor won by checkmate\"]\n[StartTime \"23:43:03\"]\n[EndDate \"2018.09.06\"]\n[EndTime \"19:58:42\"]\n[Link \"https://www.chess.com/game/daily/203173850\"]\n\n1. e4 g6 2. Bc4 h5 3. d3 b6 4. Nf3 Bb7 5. Ng5 e6 6. Nc3 Bh6 7. Nf3 a5 8. Bxh6 Rxh6 9. Qd2 f6 10. O-O-O a4 11. a3 c6 12. Ba2 b5 13. Rhe1 Qc7 14. d4 Kf7 15. e5 Na6 16. exf6 Re8 17. Ne5+ Kxf6 18. Qf4+ Ke7 19. Qf7+ Kd8 20. Nxg6 Qd6 21. d5 e5 22. dxc6 Qxc6 23. Nxe5 Rxe5 24. Qxg8+ Re8 25. Qxe8+ Kc7 26. Nd5+ Qxd5 27. Rxd5 Bxd5 28. Bxd5 Nc5 29. Qe5+ Rd6 30. Ba8 Ne6 31. Rd1 Ng5 32. Qxd6+ Kc8 33. Qxd7+ Kb8 34. Qb7# 1-0\n","time_control":"1/259200","end_time":1536263922,"rated":true,"tcn":"mC2UfA3NltXPgv6XvM0Sbs9VMvWGcV?Vdl1TeaGyiqYQAiPHhe7YtB81CK5OKT48vK1TlDT0D107KUYRBJSKJQRQUK8K1!K8!87YsJQJdJXJiJOI8KVRJ4ISedSMKRY6RZ65ZX","uuid":"6fa2ddf2-acae-11e8-8352-00000001000b","initial_setup":"rnbqkbnr/pppppppp/8/8/8/8/PPPPPPPP/RNBQKBNR w KQkq - 0 1","fen":"Bk6/1Q6/8/1p4np/p7/P7/1PP2PPP/2KR4 b - - 2 34","start_time":1535672583,"time_class":"daily","rules":"chess","white":{"rating":1433,"result":"win","@id":"https://api.chess.com/pub/player/ozzytor","username":"OzzyTor","uuid":"bae28030-220b-11e7-8008-000000000000"},"black":{"rating":1185,"result":"checkmated","@id":"https://api.chess.com/pub/player/okiedoak","username":"okiedoak","uuid":"f66f79ae-3bbd-11e0-802f-000000000000"},"eco":"https://www.chess.com/openings/Modern-Defense-with-1-e4-2.Bc4"},{"url":"https://www.chess.com/game/daily/203839250","pgn":"[Event \"Let's Play!\"]\n[Site \"Chess.com\"]\n[Date \"2018.09.07\"]\n[Round \"-\"]\n[White \"okiedoak\"]\n[Black \"OzzyTor\"]\n[Result \"0-1\"]\n[CurrentPosition \"6k1/ppp2pp1/6rp/2p5/P1P1nR2/1PP2P2/R6P/1N1r3K w - - 1 23\"]\n[Timezone \"UTC\"]\n[ECO \"C55\"]\n[ECOUrl \"https://www.chess.com/openings/Italian-Game-Two-Knights-Modern-Bishops-Opening-4...h6\"]\n[UTCDate \"2018.09.07\"]\n[UTCTime \"12:03:40\"]\n[WhiteElo \"1183\"]\n[BlackElo \"1439\"]\n[TimeControl \"1/259200\"]\n[Termination \"OzzyTor won by checkmate\"]\n[StartTime \"12:03:40\"]\n[EndDate \"2018.09.11\"]\n[EndTime \"00:07:36\"]\n[Link \"https://www.chess.com/game/daily/203839250\"]\n\n1. e4 e5 2. Bc4 Nf6 3. d3 h6 4. Nf3 Nc6 5. b3 Bc5 6. O-O d6 7. Qe1 O-O 8. Be3 Bg4 9. Bxc5 dxc5 10. c3 Bxf3 11. gxf3 Qd7 12. Kh1 Na5 13. Rg1 Nxc4 14. dxc4 Qd3 15. Rg3 Rad8 16. f4 Qxe4+ 17. Qxe4 Nxe4 18. Rf3 exf4 19. Rxf4 Rfe8 20. a4 Re6 21. Ra2 Rg6 22. f3 Rd1# 0-1\n","time_control":"1/259200","end_time":1536624456,"rated":true,"tcn":"mC0KfA!Tlt3Vgv5Qjr9IegZRde8?cu6EuIRIksEvov7ZghQGfgGAtAZtgw47vDtCeCTCwvKDvD98iy8SaiSUnv7d","uuid":"0f0b5076-b296-11e8-80fa-00000001000b","initial_setup":"rnbqkbnr/pppppppp/8/8/8/8/PPPPPPPP/RNBQKBNR w KQkq - 0 1","fen":"6k1/ppp2pp1/6rp/2p5/P1P1nR2/1PP2P2/R6P/1N1r3K w - - 1 23","start_time":1536321820,"time_class":"daily","rules":"chess","white":{"rating":1183,"result":"checkmated","@id":"https://api.chess.com/pub/player/okiedoak","username":"okiedoak","uuid":"f66f79ae-3bbd-11e0-802f-000000000000"},"black":{"rating":1439,"result":"win","@id":"https://api.chess.com/pub/player/ozzytor","username":"OzzyTor","uuid":"bae28030-220b-11e7-8008-000000000000"},"eco":"https://www.chess.com/openings/Italian-Game-Two-Knights-Modern-Bishops-Opening-4...h6"},{"url":"https://www.chess.com/game/daily/204658200","pgn":"[Event \"Let's Play!\"]\n[Site \"Chess.com\"]\n[Date \"2018.09.17\"]\n[Round \"-\"]\n[White \"OzzyTor\"]\n[Black \"okiedoak\"]\n[Result \"1-0\"]\n[CurrentPosition \"4k3/6Q1/p4P2/Pp6/1P4K1/8/2P5/8 w - - 3 65\"]\n[Timezone \"UTC\"]\n[ECO \"C40\"]\n[ECOUrl \"https://www.chess.com/openings/Kings-Pawn-Opening-Kings-Knight-Variation\"]\n[UTCDate \"2018.09.17\"]\n[UTCTime \"14:06:49\"]\n[WhiteElo \"1445\"]\n[BlackElo \"1184\"]\n[TimeControl \"1/259200\"]\n[Termination \"OzzyTor won by resignation\"]\n[StartTime \"14:06:49\"]\n[EndDate \"2018.09.30\"]\n[EndTime \"22:52:37\"]\n[Link \"https://www.chess.com/game/daily/204658200\"]\n\n1. e4 e5 2. Nf3 f6 3. Bc4 d6 4. h3 a6 5. O-O Ne7 6. d3 g6 7. Nc3 c6 8. Re1 b5 9. Bb3 h5 10. d4 h4 11. dxe5 dxe5 12. Be3 Qxd1 13. Raxd1 g5 14. Re2 Nd7 15. Red2 Rb8 16. Be6 Rb7 17. a3 Rh7 18. Bc5 Ng6 19. Bf5 Rg7 20. Bxf8 Ngxf8 21. Rd6 Rc7 22. Bxd7+ Nxd7 23. b3 Re7 24. b4 Kf7 25. R6d3 Nb6 26. Ra1 Nc4 27. a4 Nb2 28. Rd2 Be6 29. a5 Nc4 30. Rd3 g4 31. hxg4 Bxg4 32. Nxh4 Ke6 33. f3 Bh5 34. Nf5 Red7 35. Rxd7 Kxd7 36. Rd1+ Kc8 37. Nd6+ Nxd6 38. Rxd6 Rg7 39. Kf2 Rf7 40. Rxc6+ Kb7 41. Re6 Bg6 42. Nd5 Rh7 43. Rxf6 Bf7 44. Rf5 Bxd5 45. exd5 Re7 46. d6 Re6 47. Rf7+ Kc8 48. d7+ Kd8 49. g4 Rd6 50. g5 Rg6 51. Rf5 Kxd7 52. Rxe5 Kd6 53. f4 Rg7 54. Kf3 Rg8 55. Kg4 Rc8 56. Rc5 Kd7 57. Rxc8 Kxc8 58. g6 Kc7 59. g7 Kc6 60. g8=Q Kd6 61. Qg5 Kd7 62. f5 Ke8 63. f6 Kf8 64. Qg7+ Ke8 1-0\n","time_control":"1/259200","end_time":1538347957,"rated":true,"tcn":"mC0Kgv1TfAZRpxWOeh!0lt2UbsYQfeXHAr3NtBNFBKRKcu7dadUMem5Zml45rS5Xiq?3uI0USL32I9U9lRXYLZ9Zjr20rz81RtZPdaPAqyAjtl6SyGjAltMExESEvF1SnvENFL0ZtZSZadZ6LRARdRY2gn21RQ6XQSNUsJ13STU1TL1JCJ30JR0SL1X6RZ67oESREMRU1L7ZLKZRvDU2nv2!vE!6KIRZI6Z6MU6YU2YQ2~QR!MRZDLZ8LT89M298","uuid":"eb5cdcf4-ba82-11e8-80c8-00000001000b","initial_setup":"rnbqkbnr/pppppppp/8/8/8/8/PPPPPPPP/RNBQKBNR w KQkq - 0 1","fen":"4k3/6Q1/p4P2/Pp6/1P4K1/8/2P5/8 w - - 3 65","start_time":1537193209,"time_class":"daily","rules":"chess","white":{"rating":1445,"result":"win","@id":"https://api.chess.com/pub/player/ozzytor","username":"OzzyTor","uuid":"bae28030-220b-11e7-8008-000000000000"},"black":{"rating":1184,"result":"resigned","@id":"https://api.chess.com/pub/player/okiedoak","username":"okiedoak","uuid":"f66f79ae-3bbd-11e0-802f-000000000000"},"eco":"https://www.chess.com/openings/Kings-Pawn-Opening-Kings-Knight-Variation"}]}