{"games":[{"url":"https://www.chess.com/game/daily/410215879","pgn":"[Event \"Let's Play!\"]\n[Site \"Chess.com\"]\n[Date \"2022.06.19\"]\n[Round \"-\"]\n[White \"OzzyTor\"]\n[Black \"okiedoak\"]\n[Result \"1-0\"]\n[CurrentPosition \"5Q2/8/2N2kp1/3B4/2P5/8/5P1K/6R1 b - - 2 49\"]\n[Timezone \"UTC\"]\n[ECO \"C40\"]\n[ECOUrl \"https://www.chess.com/openings/Kings-Pawn-Opening-Kings-Knight-Variation\"]\n[UTCDate \"2022.06.19\"]\n[UTCTime \"23:55:39\"]\n[WhiteElo \"1683\"]\n[BlackElo \"1050\"]\n[TimeControl \"1/259200\"]\n[Termination \"OzzyTor won by checkmate\"]\n[StartTime \"23:55:39\"]\n[EndDate \"2022.07.03\"]\n[EndTime \"14:30:39\"]\n[Link \"https://www.chess.com/game/daily/410215879\"]\n\n1. e4 {[%clk 0:09:13.3]} 1... e5 {[%clk 1:49:54.4]} 2. Nf3 {[%clk 0:00:15.1]} 2... Bd6 {[%clk 0:00:03.3]} 3. c3 {[%clk 0:00:15.8]} 3... b6 {[%clk 0:29:54.4]} 4. d4 {[%clk 0:00:06.9]} 4... Bb7 {[%clk 0:00:04.6]} 5. dxe5 {[%clk 0:00:02.4]} 5... Be7 {[%clk 0:04:14.5]} 6. Bd3 {[%clk 0:02:03.3]} 6... h6 {[%clk 1:12:40]} 7. O-O {[%clk 0:02:22.3]} 7... f6 {[%clk 0:09:39.3]} 8. exf6 {[%clk 0:00:05.2]} 8... Bxf6 {[%clk 0:39:15.4]} 9. e5 {[%clk 0:06:28.2]} 9... Be7 {[%clk 1:30:40.8]} 10. Bg6+ {[%clk 0:02:40.6]} 10... Kf8 {[%clk 0:09:03.1]} 11. Re1 {[%clk 0:00:09.5]} 11... Bg5 {[%clk 0:08:22.8]} 12. Bxg5 {[%clk 0:00:07]} 12... hxg5 {[%clk 0:10:24.1]} 13. e6 {[%clk 0:00:21.8]} 13... Ke7 {[%clk 0:23:13.4]} 14. exd7+ {[%clk 0:13:23.5]} 14... Kf6 {[%clk 1:10:42.4]} 15. Qd3 {[%clk 0:00:51.4]} 15... Ne7 {[%clk 0:04:41]} 16. Be4 {[%clk 0:12:42.9]} 16... Qxd7 {[%clk 0:10:20.5]} 17. Qxd7 {[%clk 0:00:17.2]} 17... Nxd7 {[%clk 0:31:08.8]} 18. Bxb7 {[%clk 0:00:04]} 18... Raf8 {[%clk 0:06:25.7]} 19. Nbd2 {[%clk 0:00:38.3]} 19... Nc5 {[%clk 1:22:04.8]} 20. Ne4+ {[%clk 0:21:33.4]} 20... Nxe4 {[%clk 0:18:34.1]} 21. Rxe4 {[%clk 0:00:05.9]} 21... Rd8 {[%clk 0:13:09.2]} 22. h3 {[%clk 0:00:13.8]} 22... Ng6 {[%clk 0:04:23.6]} 23. Rae1 {[%clk 0:00:05]} 23... Rd6 {[%clk 1:19:38.8]} 24. b4 {[%clk 0:20:47.1]} 24... Kf5 {[%clk 0:14:16.8]} 25. Rc4 {[%clk 0:00:13.7]} 25... Nf4 {[%clk 0:09:57.7]} 26. Be4+ {[%clk 0:03:16.9]} 26... Kf6 {[%clk 0:11:43.1]} 27. Rxc7 {[%clk 0:10:52.8]} 27... a6 {[%clk 1:19:31.5]} 28. Rc6 {[%clk 0:07:20]} 28... Rxc6 {[%clk 0:27:06.2]} 29. Bxc6 {[%clk 0:02:32.3]} 29... Rc8 {[%clk 1:49:53.1]} 30. Nd4 {[%clk 0:09:58.6]} 30... Kg6 {[%clk 0:11:09.6]} 31. Re3 {[%clk 0:02:38.1]} 31... Kh7 {[%clk 0:34:21.5]} 32. Bb7 {[%clk 0:03:41]} 32... Rd8 {[%clk 1:16:44.2]} 33. Bxa6 {[%clk 0:01:42.4]} 33... Nd5 {[%clk 0:01:42.2]} 34. Rg3 {[%clk 0:00:35.6]} 34... Re8 {[%clk 0:35:58.9]} 35. Bc4 {[%clk 0:00:10.6]} 35... Re1+ {[%clk 0:28:44.2]} 36. Kh2 {[%clk 0:32:24]} 36... Kh6 {[%clk 1:26:33.4]} 37. Bxd5 {[%clk 0:13:31.5]} 37... Re5 {[%clk 0:06:19]} 38. c4 {[%clk 0:38:37.8]} 38... Re7 {[%clk 0:59:07.2]} 39. Nf5+ {[%clk 0:02:15]} 39... Kg6 {[%clk 0:35:40.5]} 40. Nxe7+ {[%clk 0:05:44.7]} 40... Kf6 {[%clk 0:08:01.6]} 41. Nc6 {[%clk 0:09:07.3]} 41... g6 {[%clk 1:06:31.4]} 42. a4 {[%clk 0:00:07.7]} 42... Kg7 {[%clk 0:29:50.1]} 43. a5 {[%clk 0:00:02.2]} 43... bxa5 {[%clk 0:00:11.4]} 44. bxa5 {[%clk 0:00:01.8]} 44... g4 {[%clk 0:31:08]} 45. a6 {[%clk 0:00:15.9]} 45... gxh3 {[%clk 1:36:52.7]} 46. a7 {[%clk 0:00:10.8]} 46... hxg2 {[%clk 0:26:13.5]} 47. a8=Q {[%clk 0:12:56.8]} 47... g1=Q+ {[%clk 0:16:35.5]} 48. Rxg1 {[%clk 0:00:05.9]} 48... Kf6 {[%clk 1:09:01.3]} 49. Qf8# {[%clk 0:04:19.1]} 1-0\n","time_control":"1/259200","end_time":1656858639,"rated":true,"accuracies":{"white":80.1,"black":72.36},"tcn":"mC0Kgv9RksXPlB6XBKR0ft3Veh1TKT0TCKT0tU89fe0McMVMKS90SZ0Tdt!0UC7ZtZ5ZCX49blZIlCICeC97px0Uae7RjzTLCAUDXCLTAYWOYQRQCQ?6vBTUeuU3QX67XODJuw78OA8egp3VAJeKsAK0BLVUL0UT0Q2UiyT2yGPGzGMEGOExOWxoW~o~wg2T49","uuid":"521f5912-f02b-11ec-b052-89064901000b","initial_setup":"rnbqkbnr/pppppppp/8/8/8/8/PPPPPPPP/RNBQKBNR w KQkq - 0 1","fen":"5Q2/8/2N2kp1/3B4/2P5/8/5P1K/6R1 b - - 2 49","start_time":1655682939,"time_class":"daily","rules":"chess","white":{"rating":1683,"result":"win","@id":"https://api.chess.com/pub/player/ozzytor","username":"OzzyTor","uuid":"bae28030-220b-11e7-8008-000000000000"},"black":{"rating":1050,"result":"checkmated","@id":"https://api.chess.com/pub/player/okiedoak","username":"okiedoak","uuid":"f66f79ae-3bbd-11e0-802f-000000000000"},"eco":"https://www.chess.com/openings/Kings-Pawn-Opening-Kings-Knight-Variation"},{"url":"https://www.chess.com/game/daily/412719901","pgn":"[Event \"Let's Play!\"]\n[Site \"Chess.com\"]\n[Date \"2022.07.01\"]\n[Round \"-\"]\n[White \"OzzyTor\"]\n[Black \"gutenberg02\"]\n[Result \"1-0\"]\n[CurrentPosition \"r1bqkbnr/pp1p1ppp/2n5/2p1p3/4P3/3P1NP1/PPP2P1P/RNBQKB1R b KQkq - 0 4\"]\n[Timezone \"UTC\"]\n[ECO \"B30\"]\n[ECOUrl \"https://www.chess.com/openings/Sicilian-Defense-Old-Sicilian-Variation-3.d3\"]\n[UTCDate \"2022.07.01\"]\n[UTCTime \"14:01:55\"]\n[WhiteElo \"1683\"]\n[BlackElo \"1200\"]\n[TimeControl \"1/172800\"]\n[Termination \"OzzyTor won on time\"]\n[StartTime \"14:01:55\"]\n[EndDate \"2022.07.03\"]\n[EndTime \"17:00:05\"]\n[Link \"https://www.chess.com/game/daily/412719901\"]\n\n1. e4 {[%clk 0:03:08.3]} 1... c5 {[%clk 0:00:02.9]} 2. Nf3 {[%clk 0:00:14.8]} 2... Nc6 {[%clk 0:00:28.4]} 3. d3 {[%clk 0:02:42.7]} 3... e5 {[%clk 0:01:31.5]} 4. g3 {[%clk 0:09:06.9]} 1-0\n","time_control":"1/172800","end_time":1656867605,"rated":false,"tcn":"mCYIgv5Qlt0Kow","uuid":"5daab9ce-f946-11ec-91c4-d6c7d301000b","initial_setup":"rnbqkbnr/pppppppp/8/8/8/8/PPPPPPPP/RNBQKBNR w KQkq - 0 1","fen":"r1bqkbnr/pp1p1ppp/2n5/2p1p3/4P3/3P1NP1/PPP2P1P/RNBQKB1R b KQkq - 0 4","start_time":1656684115,"time_class":"daily","rules":"chess","white":{"rating":1683,"result":"win","@id":"https://api.chess.com/pub/player/ozzytor","username":"OzzyTor","uuid":"bae28030-220b-11e7-8008-000000000000"},"black":{"rating":1200,"result":"timeout","@id":"https://api.chess.com/pub/player/gutenberg02","username":"gutenberg02","uuid":"3d5d5178-f463-11ec-9930-e7ab6616afbb"},"eco":"https://www.chess.com/openings/Sicilian-Defense-Old-Sicilian-Variation-3.d3"},{"url":"https://www.chess.com/game/daily/413179053","pgn":"[Event \"Let's Play!\"]\n[Site \"Chess.com\"]\n[Date \"2022.07.03\"]\n[Round \"-\"]\n[White \"seizuresqww\"]\n[Black \"OzzyTor\"]\n[Result \"0-1\"]\n[CurrentPosition \"rnbqkbnr/pp1ppppp/8/2p5/4P3/8/PPPP1PPP/RNBQKBNR w KQkq c6 0 2\"]\n[Timezone \"UTC\"]\n[ECO \"B20\"]\n[ECOUrl \"https://www.chess.com/openings/Sicilian-Defense\"]\n[UTCDate \"2022.07.03\"]\n[UTCTime \"17:52:40\"]\n[WhiteElo \"400\"]\n[BlackElo \"1683\"]\n[TimeControl \"1/172800\"]\n[Termination \"OzzyTor won on time\"]\n[StartTime \"17:52:40\"]\n[EndDate \"2022.07.05\"]\n[EndTime \"18:00:03\"]\n[Link \"https://www.chess.com/game/daily/413179053\"]\n\n1. e4 {[%clk 0:00:00.8]} 1... c5 {[%clk 0:00:02.9]} 0-1\n","time_control":"1/172800","end_time":1657044003,"rated":false,"tcn":"mCYI","uuid":"eeaff53e-faf8-11ec-bf0b-77a6cd01000b","initial_setup":"rnbqkbnr/pppppppp/8/8/8/8/PPPPPPPP/RNBQKBNR w KQkq - 0 1","fen":"rnbqkbnr/pp1ppppp/8/2p5/4P3/8/PPPP1PPP/RNBQKBNR w KQkq c6 0 2","start_time":1656870760,"time_class":"daily","rules":"chess","white":{"rating":400,"result":"timeout","@id":"https://api.chess.com/pub/player/seizuresqww","username":"seizuresqww","uuid":"d93eb412-faf6-11ec-b8db-03477dea64df"},"black":{"rating":1683,"result":"win","@id":"https://api.chess.com/pub/player/ozzytor","username":"OzzyTor","uuid":"bae28030-220b-11e7-8008-000000000000"},"eco":"https://www.chess.com/openings/Sicilian-Defense"},{"url":"https://www.chess.com/game/daily/413188515","pgn":"[Event \"Let's Play!\"]\n[Site \"Chess.com\"]\n[Date \"2022.07.03\"]\n[Round \"-\"]\n[White \"Venkey_0027\"]\n[Black \"OzzyTor\"]\n[Result \"0-1\"]\n[CurrentPosition \"rnbqkbnr/pppp1ppp/4p3/8/3P4/8/PPP1PPPP/RNBQKBNR w KQkq - 0 2\"]\n[Timezone \"UTC\"]\n[ECO \"A40\"]\n[ECOUrl \"https://www.chess.com/openings/Queens-Pawn-Opening-Horwitz-Defense\"]\n[UTCDate \"2022.07.03\"]\n[UTCTime \"18:45:17\"]\n[WhiteElo \"800\"]\n[BlackElo \"1683\"]\n[TimeControl \"1/172800\"]\n[Termination \"OzzyTor won on time\"]\n[StartTime \"18:45:17\"]\n[EndDate \"2022.07.05\"]\n[EndTime \"19:00:04\"]\n[Link \"https://www.chess.com/game/daily/413188515\"]\n\n1. d4 {[%clk 0:00:38]} 1... e6 {[%clk 0:00:08]} 0-1\n","time_control":"1/172800","end_time":1657047604,"rated":false,"accuracies":{"white":100,"black":100},"tcn":"lB0S","uuid":"4897857e-fb00-11ec-886d-a4e52601000b","initial_setup":"rnbqkbnr/pppppppp/8/8/8/8/PPPPPPPP/RNBQKBNR w KQkq - 0 1","fen":"rnbqkbnr/pppp1ppp/4p3/8/3P4/8/PPP1PPPP/RNBQKBNR w KQkq - 0 2","start_time":1656873917,"time_class":"daily","rules":"chess","white":{"rating":800,"result":"timeout","@id":"https://api.chess.com/pub/player/venkey_0027","username":"Venkey_0027","uuid":"a99e53ec-f47b-11ec-820d-81bb607f7d97"},"black":{"rating":1683,"result":"win","@id":"https://api.chess.com/pub/player/ozzytor","username":"OzzyTor","uuid":"bae28030-220b-11e7-8008-000000000000"},"eco":"https://www.chess.com/openings/Queens-Pawn-Opening-Horwitz-Defense"},{"url":"https://www.chess.com/game/daily/414557081","pgn":"[Event \"Let's Play!\"]\n[Site \"Chess.com\"]\n[Date \"2022.07.10\"]\n[Round \"-\"]\n[White \"ScottishMaiden\"]\n[Black \"OzzyTor\"]\n[Result \"0-1\"]\n[CurrentPosition \"3r2kr/ppp3pp/8/2b1p3/4P3/Pn3P2/1P3qPP/n3RK2 w - - 2 26\"]\n[Timezone \"UTC\"]\n[ECO \"A46\"]\n[ECOUrl \"https://www.chess.com/openings/Indian-Game-Knights-Variation-2...e6\"]\n[UTCDate \"2022.07.10\"]\n[UTCTime \"02:02:43\"]\n[WhiteElo \"1273\"]\n[BlackElo \"1683\"]\n[TimeControl \"1/172800\"]\n[Termination \"OzzyTor won by checkmate\"]\n[StartTime \"02:02:43\"]\n[EndDate \"2022.07.10\"]\n[EndTime \"22:32:59\"]\n[Link \"https://www.chess.com/game/daily/414557081\"]\n\n1. d4 {[%clk 0:00:04.5]} 1... Nf6 {[%clk 0:00:01.6]} 2. Nf3 {[%clk 0:00:04.7]} 2... e6 {[%clk 0:00:04.9]} 3. Ne5 {[%clk 0:00:23]} 3... d6 {[%clk 0:00:03.5]} 4. Nxf7 {[%clk 0:00:41]} 4... Kxf7 {[%clk 0:00:02.6]} 5. e3 {[%clk 0:00:02.5]} 5... Kg8 {[%clk 0:00:05.1]} 6. c4 {[%clk 0:00:27.6]} 6... Ne4 {[%clk 0:00:14]} 7. Qf3 {[%clk 0:00:15.9]} 7... Nf6 {[%clk 0:00:08.7]} 8. Bd3 {[%clk 0:01:09.5]} 8... e5 {[%clk 0:00:16]} 9. dxe5 {[%clk 0:02:04.7]} 9... dxe5 {[%clk 0:00:47.8]} 10. c5 {[%clk 1:19:57]} 10... Qxd3 {[%clk 0:00:06.3]} 11. Nd2 {[%clk 0:00:18.3]} 11... Bg4 {[%clk 0:00:17.9]} 12. Qd1 {[%clk 0:22:03.1]} 12... Bxd1 {[%clk 0:00:02.6]} 13. Kxd1 {[%clk 0:00:03.5]} 13... Nc6 {[%clk 0:00:01.6]} 14. a3 {[%clk 0:00:02.9]} 14... Ne4 {[%clk 0:00:05.4]} 15. Re1 {[%clk 0:00:04.6]} 15... Rd8 {[%clk 0:00:01.8]} 16. f3 {[%clk 0:00:04.9]} 16... Nxd2 {[%clk 0:00:00.7]} 17. Re2 {[%clk 0:09:47.3]} 17... Nb3+ {[%clk 0:00:11.4]} 18. Ke1 {[%clk 0:00:05.4]} 18... Nxa1 {[%clk 0:00:08.6]} 19. e4 {[%clk 0:00:04.4]} 19... Qd1+ {[%clk 0:00:14.4]} 20. Kf2 {[%clk 0:00:07.4]} 20... Nd4 {[%clk 0:00:01.1]} 21. Re1 {[%clk 0:00:19.2]} 21... Qc2+ {[%clk 0:00:09.7]} 22. Ke3 {[%clk 0:00:35.8]} 22... Bxc5 {[%clk 0:00:02.7]} 23. Bd2 {[%clk 0:00:54.5]} 23... Ndb3+ {[%clk 0:00:05.1]} 24. Ke2 {[%clk 0:00:02.9]} 24... Qxd2+ {[%clk 0:00:01.5]} 25. Kf1 {[%clk 0:00:01.2]} 25... Qf2# {[%clk 0:00:00.8]} 0-1\n","time_control":"1/172800","end_time":1657492379,"rated":false,"accuracies":{"white":65.54,"black":85.22},"tcn":"lB!Tgv0SvKZRK181mu1!kATCdvCTftSKBKRKAI7tbl6EvdEded5QiqTChe47nvClemlrderauCtdenQBmedknu9IclBrumklmfln","uuid":"62fa916a-fff4-11ec-ac93-deabe301000b","initial_setup":"rnbqkbnr/pppppppp/8/8/8/8/PPPPPPPP/RNBQKBNR w KQkq - 0 1","fen":"3r2kr/ppp3pp/8/2b1p3/4P3/Pn3P2/1P3qPP/n3RK2 w - - 2 26","start_time":1657418563,"time_class":"daily","rules":"chess","white":{"rating":1273,"result":"checkmated","@id":"https://api.chess.com/pub/player/scottishmaiden","username":"ScottishMaiden","uuid":"150ed63e-048a-11e7-8044-000000000000"},"black":{"rating":1683,"result":"win","@id":"https://api.chess.com/pub/player/ozzytor","username":"OzzyTor","uuid":"bae28030-220b-11e7-8008-000000000000"},"eco":"https://www.chess.com/openings/Indian-Game-Knights-Variation-2...e6"},{"url":"https://www.chess.com/game/daily/412906803","pgn":"[Event \"Let's Play!\"]\n[Site \"Chess.com\"]\n[Date \"2022.07.02\"]\n[Round \"-\"]\n[White \"ENorthE\"]\n[Black \"OzzyTor\"]\n[Result \"0-1\"]\n[CurrentPosition \"7k/pp3pp1/2p5/2P5/5P2/1n4P1/7P/4K3 w - - 1 37\"]\n[Timezone \"UTC\"]\n[ECO \"A15\"]\n[ECOUrl \"https://www.chess.com/openings/English-Opening-Anglo-Indian-Defense-2.g3-e6-3.Bg2\"]\n[UTCDate \"2022.07.02\"]\n[UTCTime \"11:51:18\"]\n[WhiteElo \"1665\"]\n[BlackElo \"1683\"]\n[TimeControl \"1/172800\"]\n[Termination \"OzzyTor won by resignation\"]\n[StartTime \"11:51:18\"]\n[EndDate \"2022.07.16\"]\n[EndTime \"16:34:13\"]\n[Link \"https://www.chess.com/game/daily/412906803\"]\n\n1. c4 {[%clk 0:17:28.1]} 1... e6 {[%clk 0:00:10.6]} 2. g3 {[%clk 0:19:31.3]} 2... Nf6 {[%clk 0:01:33.8]} 3. Bg2 {[%clk 0:01:12.8]} 3... c6 {[%clk 0:00:22.9]} 4. Nc3 {[%clk 0:00:08.9]} 4... Bb4 {[%clk 0:00:13.5]} 5. d4 {[%clk 0:19:24.4]} 5... d5 {[%clk 0:10:42.7]} 6. a3 {[%clk 0:29:10.6]} 6... Bxc3+ {[%clk 0:42:54.4]} 7. bxc3 {[%clk 1:39:14.9]} 7... dxc4 {[%clk 0:38:49.1]} 8. Nf3 {[%clk 0:25:25.5]} 8... O-O {[%clk 0:08:17.7]} 9. O-O {[%clk 0:28:27.2]} 9... Re8 {[%clk 0:15:28.6]} 10. Ne5 {[%clk 0:00:38.7]} 10... Nbd7 {[%clk 0:00:14.3]} 11. Nxc4 {[%clk 0:00:35.9]} 11... e5 {[%clk 0:00:15.3]} 12. dxe5 {[%clk 0:00:18.5]} 12... Nd5 {[%clk 0:00:11]} 13. Nd6 {[%clk 0:00:39.4]} 13... Rxe5 {[%clk 0:02:43.9]} 14. c4 {[%clk 0:01:04.2]} 14... Nc3 {[%clk 0:00:11.5]} 15. Qc2 {[%clk 0:00:21.6]} 15... Nxe2+ {[%clk 0:00:04.2]} 16. Kh1 {[%clk 0:00:02.3]} 16... Nxc1 {[%clk 0:00:08.5]} 17. Raxc1 {[%clk 0:00:02.4]} 17... Qe7 {[%clk 0:00:02.5]} 18. f4 {[%clk 0:00:37.3]} 18... Re6 {[%clk 0:00:12.5]} 19. c5 {[%clk 0:00:25.7]} 19... Nf6 {[%clk 0:49:30.8]} 20. Qb3 {[%clk 1:21:13.2]} 20... Ne8 {[%clk 0:03:31.1]} 21. Nf5 {[%clk 6:20:57.3]} 21... Qf6 {[%clk 1:16:59.1]} 22. Bh3 {[%clk 0:57:00.3]} 22... Re2 {[%clk 0:00:06.7]} 23. Qd3 {[%clk 0:04:38.4]} 23... Bxf5 {[%clk 0:05:31.8]} 24. Bxf5 {[%clk 4:38:46.8]} 24... Qb2 {[%clk 0:09:01.8]} 25. Bxh7+ {[%clk 0:03:15.7]} 25... Kh8 {[%clk 0:00:06.7]} 26. Rc2 {[%clk 0:01:33.4]} 26... Rxc2 {[%clk 0:00:07.2]} 27. Qxc2 {[%clk 0:00:04.3]} 27... Qxa3 {[%clk 0:00:02.1]} 28. Be4 {[%clk 1:44:28]} 28... Nf6 {[%clk 0:00:08.1]} 29. Bf3 {[%clk 1:08:14.1]} 29... Re8 {[%clk 0:27:34.7]} 30. Rb1 {[%clk 0:36:18.4]} 30... Qxf3+ {[%clk 0:00:11.6]} 31. Qg2 {[%clk 0:01:55.3]} 31... Qxg2+ {[%clk 0:01:39.3]} 32. Kxg2 {[%clk 0:00:02.1]} 32... Re7 {[%clk 0:00:04.1]} 33. Kf3 {[%clk 0:00:50.8]} 33... Ne4 {[%clk 0:00:07.7]} 34. Re1 {[%clk 0:00:04.7]} 34... Nd2+ {[%clk 0:00:11.8]} 35. Kf2 {[%clk 0:00:10.2]} 35... Rxe1 {[%clk 0:00:05]} 36. Kxe1 {[%clk 0:00:01.3]} 36... Nb3 {[%clk 0:00:01.2]} 0-1\n","time_control":"1/172800","end_time":1657989253,"rated":false,"accuracies":{"white":79.92,"black":86.3},"tcn":"kA0Sow!TfoYQbs9zlBZJiqzsjsJAgv8?eh98vK5ZKASKBKTJAR8KsAJsdksmghmcac70nDKSAIZTkrT8RL0ToxSmrt6LxLTjL3!?ckmktkjq3C8TCv48fbqvkovoho80ovTCbeClvn0enelr","uuid":"489f7788-f9fd-11ec-8faa-cd0c1401000b","initial_setup":"rnbqkbnr/pppppppp/8/8/8/8/PPPPPPPP/RNBQKBNR w KQkq - 0 1","fen":"7k/pp3pp1/2p5/2P5/5P2/1n4P1/7P/4K3 w - - 1 37","start_time":1656762678,"time_class":"daily","rules":"chess","white":{"rating":1665,"result":"resigned","@id":"https://api.chess.com/pub/player/enorthe","username":"ENorthE","uuid":"9b8350e0-907f-11e9-8980-3d46a176aa80"},"black":{"rating":1683,"result":"win","@id":"https://api.chess.com/pub/player/ozzytor","username":"OzzyTor","uuid":"bae28030-220b-11e7-8008-000000000000"},"eco":"https://www.chess.com/openings/English-Opening-Anglo-Indian-Defense-2.g3-e6-3.Bg2"},{"url":"https://www.chess.com/game/daily/416107755","pgn":"[Event \"Let's Play!\"]\n[Site \"Chess.com\"]\n[Date \"2022.07.17\"]\n[Round \"-\"]\n[White \"coonormogn\"]\n[Black \"OzzyTor\"]\n[Result \"1-0\"]\n[CurrentPosition \"rnbqkbnr/pp1ppppp/8/2p5/4P3/8/PPPP1PPP/RNBQKBNR w KQkq c6 0 2\"]\n[Timezone \"UTC\"]\n[ECO \"B20\"]\n[ECOUrl \"https://www.chess.com/openings/Sicilian-Defense\"]\n[UTCDate \"2022.07.17\"]\n[UTCTime \"02:16:11\"]\n[WhiteElo \"400\"]\n[BlackElo \"1683\"]\n[TimeControl \"1/172800\"]\n[Termination \"coonormogn won by resignation\"]\n[StartTime \"02:16:11\"]\n[EndDate \"2022.07.17\"]\n[EndTime \"04:04:15\"]\n[Link \"https://www.chess.com/game/daily/416107755\"]\n\n1. e4 {[%clk 0:00:02.3]} 1... c5 {[%clk 0:00:02.3]} 1-0\n","time_control":"1/172800","end_time":1658030655,"rated":false,"tcn":"mCYI","uuid":"6d324326-0576-11ed-baf3-6fb9c101000b","initial_setup":"rnbqkbnr/pppppppp/8/8/8/8/PPPPPPPP/RNBQKBNR w KQkq - 0 1","fen":"rnbqkbnr/pp1ppppp/8/2p5/4P3/8/PPPP1PPP/RNBQKBNR w KQkq c6 0 2","start_time":1658024171,"time_class":"daily","rules":"chess","white":{"rating":400,"result":"win","@id":"https://api.chess.com/pub/player/coonormogn","username":"coonormogn","uuid":"79f69bae-b57f-11eb-8e51-69aa34e6b04a"},"black":{"rating":1683,"result":"resigned","@id":"https://api.chess.com/pub/player/ozzytor","username":"OzzyTor","uuid":"bae28030-220b-11e7-8008-000000000000"},"eco":"https://www.chess.com/openings/Sicilian-Defense"},{"url":"https://www.chess.com/game/daily/416107635","pgn":"[Event \"Let's Play!\"]\n[Site \"Chess.com\"]\n[Date \"2022.07.17\"]\n[Round \"-\"]\n[White \"daySleepR\"]\n[Black \"OzzyTor\"]\n[Result \"1-0\"]\n[CurrentPosition \"q3nk1Q/7p/6p1/1N6/2P1P3/1r6/5PPP/5RK1 b - - 1 31\"]\n[Timezone \"UTC\"]\n[ECO \"B20\"]\n[ECOUrl \"https://www.chess.com/openings/Sicilian-Defense-Bowdler-Attack\"]\n[UTCDate \"2022.07.17\"]\n[UTCTime \"02:15:16\"]\n[WhiteElo \"1473\"]\n[BlackElo \"1683\"]\n[TimeControl \"1/172800\"]\n[Termination \"daySleepR won by resignation\"]\n[StartTime \"02:15:16\"]\n[EndDate \"2022.07.17\"]\n[EndTime \"04:13:06\"]\n[Link \"https://www.chess.com/game/daily/416107635\"]\n\n1. e4 {[%clk 0:00:00.5]} 1... c5 {[%clk 0:00:09.2]} 2. Bc4 {[%clk 0:01:03.2]} 2... d6 {[%clk 0:00:11.3]} 3. Qh5 {[%clk 0:00:25]} 3... g6 {[%clk 0:00:06.4]} 4. Qd5 {[%clk 0:00:21.5]} 4... e6 {[%clk 0:00:02.5]} 5. Bb5+ {[%clk 0:00:02.6]} 5... Bd7 {[%clk 0:00:01.3]} 6. Qxb7 {[%clk 0:00:02]} 6... Bxb5 {[%clk 0:00:04.3]} 7. Qxb5+ {[%clk 0:00:04.5]} 7... Nd7 {[%clk 0:00:01.9]} 8. Nf3 {[%clk 0:00:11.1]} 8... Bg7 {[%clk 0:00:04.1]} 9. Qc6 {[%clk 0:00:05.7]} 9... Be5 {[%clk 0:00:09.6]} 10. Nxe5 {[%clk 0:00:04.9]} 10... dxe5 {[%clk 0:00:01.2]} 11. b3 {[%clk 0:00:06]} 11... Nf6 {[%clk 0:00:02.5]} 12. Bb2 {[%clk 0:00:03.7]} 12... O-O {[%clk 0:00:05.4]} 13. O-O {[%clk 0:00:31.9]} 13... Rc8 {[%clk 0:00:12.9]} 14. Qa4 {[%clk 0:00:20.9]} 14... Rc7 {[%clk 0:00:07.7]} 15. Qc4 {[%clk 0:00:08]} 15... Nb6 {[%clk 0:00:03.3]} 16. Qe2 {[%clk 0:00:10.9]} 16... Nbd7 {[%clk 0:00:06.2]} 17. c4 {[%clk 0:00:09.5]} 17... Qa8 {[%clk 0:00:04.5]} 18. d3 {[%clk 0:00:02.7]} 18... a5 {[%clk 0:00:01.4]} 19. Nc3 {[%clk 0:00:04.7]} 19... Rd8 {[%clk 0:00:17.8]} 20. Rad1 {[%clk 0:00:16.7]} 20... Nb6 {[%clk 0:00:14.2]} 21. Nb5 {[%clk 0:00:19.1]} 21... Rcd7 {[%clk 0:00:08.3]} 22. Bxe5 {[%clk 0:00:08.8]} 22... Ne8 {[%clk 0:00:03.5]} 23. Rd2 {[%clk 0:01:44.5]} 23... a4 {[%clk 0:00:08.8]} 24. Qe3 {[%clk 0:00:16.2]} 24... axb3 {[%clk 0:00:14.6]} 25. axb3 {[%clk 0:00:03.5]} 25... f6 {[%clk 0:00:11.3]} 26. Qxc5 {[%clk 0:00:22.2]} 26... Rxd3 {[%clk 0:00:15.7]} 27. Rxd3 {[%clk 0:00:16.7]} 27... Rxd3 {[%clk 0:00:05]} 28. Qxb6 {[%clk 0:00:23.8]} 28... fxe5 {[%clk 0:00:05.3]} 29. Qxe6+ {[%clk 0:00:01.1]} 29... Kf8 {[%clk 0:00:01.9]} 30. Qxe5 {[%clk 0:00:05.3]} 30... Rxb3 {[%clk 0:00:05.9]} 31. Qh8+ {[%clk 0:00:18.4]} 1-0\n","time_control":"1/172800","end_time":1658031186,"rated":false,"accuracies":{"white":87.63,"black":76.6},"tcn":"mCYIfAZRdN2UNJ0SAH6ZJXZHXH5Zgv92HQ2KvKRKjr!Tcj8?eh46Qy6YyAZPAmPZkA74ltWGbs97adZPsHYZjKT8dlGymuyrir1TuIZtlt7tIPTKPS!9SKtrK?","uuid":"4c933332-0576-11ed-99ff-028ffe01000b","initial_setup":"rnbqkbnr/pppppppp/8/8/8/8/PPPPPPPP/RNBQKBNR w KQkq - 0 1","fen":"q3nk1Q/7p/6p1/1N6/2P1P3/1r6/5PPP/5RK1 b - - 1 31","start_time":1658024116,"time_class":"daily","rules":"chess","white":{"rating":1473,"result":"win","@id":"https://api.chess.com/pub/player/daysleepr","username":"daySleepR","uuid":"b1471bc2-0671-11e7-8024-000000000000"},"black":{"rating":1683,"result":"resigned","@id":"https://api.chess.com/pub/player/ozzytor","username":"OzzyTor","uuid":"bae28030-220b-11e7-8008-000000000000"},"eco":"https://www.chess.com/openings/Sicilian-Defense-Bowdler-Attack"},{"url":"https://www.chess.com/game/daily/416298439","pgn":"[Event \"Let's Play!\"]\n[Site \"Chess.com\"]\n[Date \"2022.07.17\"]\n[Round \"-\"]\n[White \"Shraygupta28\"]\n[Black \"OzzyTor\"]\n[Result \"0-1\"]\n[CurrentPosition \"6k1/5ppp/4P3/8/8/6P1/1r5P/1q3K2 w - - 0 38\"]\n[Timezone \"UTC\"]\n[ECO \"A23\"]\n[ECOUrl \"https://www.chess.com/openings/English-Opening-Carls-Bremen-Keres-Variation-4.Bg2\"]\n[UTCDate \"2022.07.17\"]\n[UTCTime \"22:56:32\"]\n[WhiteElo \"981\"]\n[BlackElo \"1683\"]\n[TimeControl \"1/172800\"]\n[Termination \"OzzyTor won by checkmate\"]\n[StartTime \"22:56:32\"]\n[EndDate \"2022.07.19\"]\n[EndTime \"19:50:51\"]\n[Link \"https://www.chess.com/game/daily/416298439\"]\n\n1. c4 {[%clk 0:00:14.5]} 1... e5 {[%clk 0:00:27.2]} 2. Nc3 {[%clk 0:00:02]} 2... Nf6 {[%clk 0:00:00.7]} 3. g3 {[%clk 0:00:02.1]} 3... c6 {[%clk 0:00:01.2]} 4. Bg2 {[%clk 0:00:01.7]} 4... Bb4 {[%clk 0:00:04.4]} 5. e3 {[%clk 0:09:57]} 5... O-O {[%clk 0:01:33.3]} 6. Nge2 {[%clk 0:00:19.6]} 6... d6 {[%clk 0:09:59.7]} 7. O-O {[%clk 0:27:16.3]} 7... Be6 {[%clk 0:20:56]} 8. a3 {[%clk 0:04:00.8]} 8... Bxc3 {[%clk 0:02:26.6]} 9. bxc3 {[%clk 0:03:53.5]} 9... Bxc4 {[%clk 0:26:08.7]} 10. Bb2 {[%clk 0:00:16.2]} 10... Re8 {[%clk 0:00:06.8]} 11. d3 {[%clk 0:03:28.2]} 11... Bd5 {[%clk 0:02:43.9]} 12. e4 {[%clk 0:01:11.4]} 12... Be6 {[%clk 0:00:22.2]} 13. c4 {[%clk 0:00:29.8]} 13... Nbd7 {[%clk 0:00:14.1]} 14. Nc3 {[%clk 0:00:01.4]} 14... Nb6 {[%clk 0:02:19.3]} 15. a4 {[%clk 0:25:30.6]} 15... d5 {[%clk 0:00:32.2]} 16. cxd5 {[%clk 0:00:40.7]} 16... cxd5 {[%clk 0:00:10]} 17. exd5 {[%clk 0:00:02]} 17... Nbxd5 {[%clk 0:00:05]} 18. f4 {[%clk 0:00:05.3]} 18... Ne3 {[%clk 0:00:28.5]} 19. Qe2 {[%clk 0:02:04.2]} 19... Nxf1 {[%clk 0:32:28.1]} 20. Qxf1 {[%clk 0:12:10.8]} 20... Qb6+ {[%clk 0:22:36.5]} 21. Kh1 {[%clk 0:09:06.1]} 21... Qxb2 {[%clk 0:00:35.8]} 22. Ne4 {[%clk 0:00:07.4]} 22... Nxe4 {[%clk 0:00:53.4]} 23. Bxe4 {[%clk 0:00:07.1]} 23... exf4 {[%clk 0:00:29.3]} 24. Rb1 {[%clk 0:00:24.4]} 24... Qa3 {[%clk 0:00:33.7]} 25. Rxb7 {[%clk 0:00:04.7]} 25... Qxa4 {[%clk 0:00:19]} 26. Rb1 {[%clk 0:00:17.2]} 26... Rab8 {[%clk 0:00:03.7]} 27. Rxb8 {[%clk 0:00:08.9]} 27... Rxb8 {[%clk 0:00:07.1]} 28. Qxf4 {[%clk 0:03:42.8]} 28... Rb1+ {[%clk 0:00:11.3]} 29. Kg2 {[%clk 0:00:13.1]} 29... Qc2+ {[%clk 0:00:32.2]} 30. Qf2 {[%clk 0:02:32.3]} 30... Qxf2+ {[%clk 0:00:02.6]} 31. Kxf2 {[%clk 0:05:15.2]} 31... a5 {[%clk 0:00:02.2]} 32. d4 {[%clk 0:01:27.6]} 32... Rb2+ {[%clk 0:00:52.9]} 33. Kg1 {[%clk 0:00:29.3]} 33... a4 {[%clk 0:01:56]} 34. Kf1 {[%clk 0:00:18.9]} 34... a3 {[%clk 0:02:41.2]} 35. d5 {[%clk 0:17:32]} 35... a2 {[%clk 0:00:01.8]} 36. dxe6 {[%clk 0:01:26.4]} 36... a1=Q+ {[%clk 0:00:10.7]} 37. Bb1 {[%clk 0:00:18.7]} 37... Qxb1# {[%clk 0:00:48.4]} 0-1\n","time_control":"1/172800","end_time":1658260251,"rated":false,"accuracies":{"white":75.29,"black":89.03},"tcn":"kA0Kbs!TowYQfo9zmu8?gmZReh6SiqzsjsSAcj98ltAJuCJSsA5ZmsZPqyRJAJQJCJPJnDJudmufmf7PghPjsCTCoCKDabjqbXqyXb45b585fD5bhoykDnknonWGtBbjngGygfyqBJqiJSi~Cbab","uuid":"b3ab4bc4-0623-11ed-8ff6-a3f99201000b","initial_setup":"rnbqkbnr/pppppppp/8/8/8/8/PPPPPPPP/RNBQKBNR w KQkq - 0 1","fen":"6k1/5ppp/4P3/8/8/6P1/1r5P/1q3K2 w - - 0 38","start_time":1658098592,"time_class":"daily","rules":"chess","white":{"rating":981,"result":"checkmated","@id":"https://api.chess.com/pub/player/shraygupta28","username":"Shraygupta28","uuid":"e81a352e-d5c8-11ea-b0dd-6b7433bb619b"},"black":{"rating":1683,"result":"win","@id":"https://api.chess.com/pub/player/ozzytor","username":"OzzyTor","uuid":"bae28030-220b-11e7-8008-000000000000"},"eco":"https://www.chess.com/openings/English-Opening-Carls-Bremen-Keres-Variation-4.Bg2"},{"url":"https://www.chess.com/game/daily/416119977","pgn":"[Event \"Let's Play!\"]\n[Site \"Chess.com\"]\n[Date \"2022.07.17\"]\n[Round \"-\"]\n[White \"Roz_79\"]\n[Black \"OzzyTor\"]\n[Result \"0-1\"]\n[CurrentPosition \"r3k1nr/1p1b1p1p/2n1p1p1/1q2P1B1/1b1p3P/2N5/P1P1NPP1/R3K2R w KQkq - 0 15\"]\n[Timezone \"UTC\"]\n[ECO \"B20\"]\n[ECOUrl \"https://www.chess.com/openings/Sicilian-Defense\"]\n[UTCDate \"2022.07.17\"]\n[UTCTime \"04:17:43\"]\n[WhiteElo \"1002\"]\n[BlackElo \"1683\"]\n[TimeControl \"1/172800\"]\n[Termination \"OzzyTor won by resignation\"]\n[StartTime \"04:17:43\"]\n[EndDate \"2022.07.20\"]\n[EndTime \"10:00:10\"]\n[Link \"https://www.chess.com/game/daily/416119977\"]\n\n1. e4 {[%clk 0:00:01.2]} 1... c5 {[%clk 0:00:01.9]} 2. Qh5 {[%clk 0:43:54.7]} 2... d6 {[%clk 0:01:28.4]} 3. Bc4 {[%clk 0:01:21.2]} 3... e6 {[%clk 0:00:08.5]} 4. e5 {[%clk 1:44:24.6]} 4... g6 {[%clk 0:31:29.7]} 5. Qe2 {[%clk 0:18:51.9]} 5... d5 {[%clk 0:17:33.5]} 6. Bb5+ {[%clk 1:16:31.6]} 6... Nc6 {[%clk 0:00:10.3]} 7. d4 {[%clk 0:01:23.5]} 7... Bd7 {[%clk 0:00:05.8]} 8. dxc5 {[%clk 0:00:03.1]} 8... Bxc5 {[%clk 0:01:45.3]} 9. h4 {[%clk 0:00:05.7]} 9... a6 {[%clk 0:00:01.9]} 10. Bg5 {[%clk 0:00:16]} 10... Qa5+ {[%clk 0:00:06.8]} 11. Nc3 {[%clk 0:18:54.5]} 11... axb5 {[%clk 0:08:40.7]} 12. b4 {[%clk 0:07:46.1]} 12... Bxb4 {[%clk 0:01:59.4]} 13. Qxb5 {[%clk 1:04:34.8]} 13... Qxb5 {[%clk 0:06:13.4]} 14. Ne2 {[%clk 0:33:36]} 14... d4 {[%clk 0:17:03]} 0-1\n","time_control":"1/172800","end_time":1658311210,"rated":false,"accuracies":{"white":57.96,"black":85.03},"tcn":"mCYIdNZRfA0SCK2UNmRJAH5QlB6ZBI9IpFWOcM7GbsOHjzIzmHGHgmJB","uuid":"675c5fca-0587-11ed-8c76-62947a01000b","initial_setup":"rnbqkbnr/pppppppp/8/8/8/8/PPPPPPPP/RNBQKBNR w KQkq - 0 1","fen":"r3k1nr/1p1b1p1p/2n1p1p1/1q2P1B1/1b1p3P/2N5/P1P1NPP1/R3K2R w KQkq - 0 15","start_time":1658031463,"time_class":"daily","rules":"chess","white":{"rating":1002,"result":"resigned","@id":"https://api.chess.com/pub/player/roz_79","username":"Roz_79","uuid":"5620e79a-8661-11eb-b57f-d5d45633a300"},"black":{"rating":1683,"result":"win","@id":"https://api.chess.com/pub/player/ozzytor","username":"OzzyTor","uuid":"bae28030-220b-11e7-8008-000000000000"},"eco":"https://www.chess.com/openings/Sicilian-Defense"},{"url":"https://www.chess.com/game/daily/413191679","pgn":"[Event \"Let's Play!\"]\n[Site \"Chess.com\"]\n[Date \"2022.07.03\"]\n[Round \"-\"]\n[White \"okiedoak\"]\n[Black \"OzzyTor\"]\n[Result \"0-1\"]\n[CurrentPosition \"5k2/5pb1/6p1/4p3/4P3/8/2q5/3rK3 w - - 6 49\"]\n[Timezone \"UTC\"]\n[ECO \"B20\"]\n[ECOUrl \"https://www.chess.com/openings/Sicilian-Defense-Staunton-Cochrane-Variation\"]\n[UTCDate \"2022.07.03\"]\n[UTCTime \"19:03:29\"]\n[WhiteElo \"1049\"]\n[BlackElo \"1685\"]\n[TimeControl \"1/259200\"]\n[Termination \"OzzyTor won by checkmate\"]\n[StartTime \"19:03:29\"]\n[EndDate \"2022.07.26\"]\n[EndTime \"13:26:16\"]\n[Link \"https://www.chess.com/game/daily/413191679\"]\n\n1. e4 {[%clk 0:00:02.1]} 1... c5 {[%clk 0:00:03.7]} 2. c4 {[%clk 0:00:05.3]} 2... d6 {[%clk 0:00:01.4]} 3. d3 {[%clk 0:23:59.1]} 3... Nf6 {[%clk 0:01:39.3]} 4. f3 {[%clk 1:21:10.2]} 4... g6 {[%clk 0:09:43]} 5. g4 {[%clk 0:12:45.6]} 5... Bg7 {[%clk 0:00:07.5]} 6. a4 {[%clk 0:24:36.4]} 6... O-O {[%clk 0:17:07.5]} 7. Nc3 {[%clk 0:14:13.4]} 7... Nc6 {[%clk 0:39:30.5]} 8. Bd2 {[%clk 1:03:44.6]} 8... Re8 {[%clk 0:03:31.4]} 9. h4 {[%clk 0:11:49.5]} 9... Nd4 {[%clk 0:00:18.9]} 10. Rh3 {[%clk 0:16:00]} 10... h5 {[%clk 0:00:06.1]} 11. Be3 {[%clk 1:25:50.2]} 11... hxg4 {[%clk 0:00:13.8]} 12. Rg3 {[%clk 0:27:07]} 12... gxf3 {[%clk 0:00:19.8]} 13. Kf2 {[%clk 2:17:33.5]} 13... Ng4+ {[%clk 0:02:40.1]} 14. Ke1 {[%clk 0:27:43.6]} 14... Nxe3 {[%clk 0:03:28]} 15. Qd2 {[%clk 0:04:37]} 15... Nec2+ {[%clk 0:00:13.7]} 16. Kf2 {[%clk 2:17:02.4]} 16... Nxa1 {[%clk 0:24:20.5]} 17. Nxf3 {[%clk 1:09:43.6]} 17... Nxf3 {[%clk 0:00:04.5]} 18. Rxf3 {[%clk 0:35:15]} 18... e5 {[%clk 0:11:55.2]} 19. Kg3 {[%clk 1:24:50.7]} 19... Re6 {[%clk 0:03:57.4]} 20. Bh3 {[%clk 0:57:12.9]} 20... Rf6 {[%clk 0:00:03]} 21. Bxc8 {[%clk 0:00:07.1]} 21... Rxf3+ {[%clk 0:00:02.3]} 22. Kxf3 {[%clk 1:28:41.5]} 22... Rxc8 {[%clk 0:15:42.4]} 23. Qd1 {[%clk 0:13:13.3]} 23... Qf6+ {[%clk 0:00:02.8]} 24. Kg2 {[%clk 2:12:35.1]} 24... Nb3 {[%clk 0:12:22.4]} 25. Qxb3 {[%clk 0:25:14.2]} 25... b6 {[%clk 0:00:59.2]} 26. Nd5 {[%clk 1:47:10.2]} 26... Qxh4 {[%clk 0:00:11.3]} 27. Qc2 {[%clk 2:58:19.7]} 27... Kh7 {[%clk 0:56:30.4]} 28. Qe2 {[%clk 2:55:05.6]} 28... Rh8 {[%clk 0:00:09]} 29. Qf3 {[%clk 0:57:36.3]} 29... Kg8 {[%clk 0:01:39.4]} 30. Kg1 {[%clk 2:13:42]} 30... Qh2+ {[%clk 0:03:17.4]} 31. Kf1 {[%clk 2:33:18.2]} 31... Rh3 {[%clk 0:29:08.1]} 32. Qg2 {[%clk 1:14:46.6]} 32... Qxg2+ {[%clk 0:08:27.5]} 33. Kxg2 {[%clk 0:17:22.8]} 33... Rxd3 {[%clk 0:00:35]} 34. Ne7+ {[%clk 0:16:34.8]} 34... Kf8 {[%clk 0:00:02.7]} 35. Nc8 {[%clk 1:20:18.3]} 35... Rd2+ {[%clk 0:16:47.5]} 36. Kf3 {[%clk 0:42:58.8]} 36... Rxb2 {[%clk 0:00:09.6]} 37. Nxa7 {[%clk 1:33:08.9]} 37... Ra2 {[%clk 0:00:19.8]} 38. Nc8 {[%clk 0:11:21.3]} 38... Rxa4 {[%clk 0:01:00.9]} 39. Nxb6 {[%clk 0:20:25.2]} 39... Rxc4 {[%clk 0:16:59.8]} 40. Nc8 {[%clk 0:07:40.3]} 40... Rd4 {[%clk 0:04:51.6]} 41. Nxd6 {[%clk 1:12:52.3]} 41... Rxd6 {[%clk 0:00:12.2]} 42. Kg4 {[%clk 3:14:17.3]} 42... c4 {[%clk 0:00:06.3]} 43. Kg5 {[%clk 0:14:44]} 43... c3 {[%clk 0:00:22.5]} 44. Kg4 {[%clk 1:32:39.6]} 44... c2 {[%clk 0:00:05.7]} 45. Kf3 {[%clk 0:00:26.4]} 45... c1=Q {[%clk 0:00:01.8]} 46. Kf2 {[%clk 0:46:25.1]} 46... Rd3 {[%clk 0:00:40.8]} 47. Ke2 {[%clk 1:33:04.5]} 47... Qc2+ {[%clk 0:04:02.1]} 48. Ke1 {[%clk 2:04:13.7]} 48... Rd1# {[%clk 0:00:15.7]} 0-1\n","time_control":"1/259200","end_time":1658841976,"rated":true,"accuracies":{"white":79.66,"black":89.66},"tcn":"mCYIkAZRlt!Tnv2UoE92iy8?bs5Qcl98pFQBhx3NluNExwEvenTEneEudlukenkagvBvwv0Knw8SfxSTx6Tvwv46ld7TvoardrXPsJTFrk!3km6?mv3!ogFpgf?xvopofoxtJ0!906tlovlj6WjiW6iy6PyAP6AB6RBRvEIAEMAsMEskEvk~vnRtnmckmetd","uuid":"d3660890-fb02-11ec-bbb1-fc4fb201000b","initial_setup":"rnbqkbnr/pppppppp/8/8/8/8/PPPPPPPP/RNBQKBNR w KQkq - 0 1","fen":"5k2/5pb1/6p1/4p3/4P3/8/2q5/3rK3 w - - 6 49","start_time":1656875009,"time_class":"daily","rules":"chess","white":{"rating":1049,"result":"checkmated","@id":"https://api.chess.com/pub/player/okiedoak","username":"okiedoak","uuid":"f66f79ae-3bbd-11e0-802f-000000000000"},"black":{"rating":1685,"result":"win","@id":"https://api.chess.com/pub/player/ozzytor","username":"OzzyTor","uuid":"bae28030-220b-11e7-8008-000000000000"},"eco":"https://www.chess.com/openings/Sicilian-Defense-Staunton-Cochrane-Variation"},{"url":"https://www.chess.com/game/daily/417471221","pgn":"[Event \"Let's Play!\"]\n[Site \"Chess.com\"]\n[Date \"2022.07.23\"]\n[Round \"-\"]\n[White \"WhyteRabbittt\"]\n[Black \"OzzyTor\"]\n[Result \"1-0\"]\n[CurrentPosition \"8/8/K3kBp1/6P1/2p5/2P4b/7P/8 w - - 1 54\"]\n[Timezone \"UTC\"]\n[ECO \"E00\"]\n[ECOUrl \"https://www.chess.com/openings/Indian-Game-East-Indian-Defense-3.Nc3\"]\n[UTCDate \"2022.07.23\"]\n[UTCTime \"01:25:57\"]\n[WhiteElo \"1355\"]\n[BlackElo \"1685\"]\n[TimeControl \"1/172800\"]\n[Termination \"WhyteRabbittt won by resignation\"]\n[StartTime \"01:25:57\"]\n[EndDate \"2022.07.30\"]\n[EndTime \"23:05:45\"]\n[Link \"https://www.chess.com/game/daily/417471221\"]\n\n1. c4 {[%clk 0:00:00.4]} 1... Nf6 {[%clk 0:00:02.5]} 2. d4 {[%clk 0:01:38.5]} 2... e6 {[%clk 0:00:18]} 3. Nc3 {[%clk 0:00:57.4]} 3... g6 {[%clk 0:00:10.1]} 4. Bg5 {[%clk 2:21:34]} 4... Bg7 {[%clk 0:00:59.7]} 5. e4 {[%clk 0:09:55.2]} 5... d6 {[%clk 0:00:08.8]} 6. Nf3 {[%clk 1:09:23.4]} 6... O-O {[%clk 0:05:16.7]} 7. Bd3 {[%clk 0:11:01.5]} 7... Re8 {[%clk 0:00:26.8]} 8. O-O {[%clk 0:03:01.1]} 8... h6 {[%clk 0:01:44]} 9. Bh4 {[%clk 0:21:32]} 9... Nbd7 {[%clk 0:08:17.6]} 10. e5 {[%clk 0:01:55.8]} 10... dxe5 {[%clk 0:00:16.5]} 11. dxe5 {[%clk 0:03:48.2]} 11... Nxe5 {[%clk 0:00:45]} 12. Nxe5 {[%clk 0:02:09.1]} 12... Qd4 {[%clk 0:02:37.9]} 13. Nf3 {[%clk 0:01:18.9]} 13... Qb6 {[%clk 0:00:18.4]} 14. Qc2 {[%clk 0:00:50.2]} 14... Nh5 {[%clk 0:01:32.3]} 15. Rab1 {[%clk 0:06:42.2]} 15... Nf4 {[%clk 1:15:28.5]} 16. Bg3 {[%clk 0:22:28.2]} 16... Nxd3 {[%clk 0:00:06.2]} 17. Qxd3 {[%clk 0:02:58.6]} 17... e5 {[%clk 0:21:43.7]} 18. Nd5 {[%clk 0:04:45.1]} 18... Qd6 {[%clk 0:00:44.6]} 19. Nd4 {[%clk 0:01:46]} 19... c6 {[%clk 0:01:29]} 20. Rbe1 {[%clk 0:06:19.8]} 20... cxd5 {[%clk 0:37:47.3]} 21. Nb5 {[%clk 0:41:51.1]} 21... Qb4 {[%clk 0:08:40.2]} 22. Nc7 {[%clk 0:30:45.8]} 22... dxc4 {[%clk 0:01:34.8]} 23. Qc3 {[%clk 0:02:06]} 23... Qxc3 {[%clk 0:04:05.6]} 24. bxc3 {[%clk 0:04:53.5]} 24... Bf5 {[%clk 0:01:56.9]} 25. Nxa8 {[%clk 0:01:47.2]} 25... Bd3 {[%clk 0:00:12.2]} 26. Nc7 {[%clk 0:02:37.4]} 26... Re7 {[%clk 0:55:01.4]} 27. Nd5 {[%clk 0:12:08.1]} 27... Rd7 {[%clk 0:01:39.9]} 28. Bxe5 {[%clk 0:16:24.3]} 28... Rxd5 {[%clk 0:03:37.1]} 29. Bxg7 {[%clk 0:10:35.9]} 29... Bxf1 {[%clk 0:01:37.5]} 30. Bxh6 {[%clk 0:12:40.1]} 30... Be2 {[%clk 0:00:11.9]} 31. f3 {[%clk 0:12:20.8]} 31... Rd1 {[%clk 0:08:46.1]} 32. Kf2 {[%clk 0:01:33.9]} 32... Rxe1 {[%clk 0:02:24.9]} 33. Kxe1 {[%clk 0:03:25.2]} 33... Bd3 {[%clk 0:04:21.2]} 34. Kd2 {[%clk 0:01:14.2]} 34... b5 {[%clk 0:53:13.8]} 35. a3 {[%clk 0:08:54.4]} 35... a6 {[%clk 0:26:03.9]} 36. Be3 {[%clk 0:11:55.9]} 36... f5 {[%clk 0:00:04.3]} 37. g4 {[%clk 0:01:41]} 37... fxg4 {[%clk 0:00:05.1]} 38. fxg4 {[%clk 0:01:32.2]} 38... Kg7 {[%clk 0:00:25.2]} 39. g5 {[%clk 0:02:22.3]} 39... Bf5 {[%clk 0:00:04.4]} 40. Bb6 {[%clk 0:00:03.3]} 40... Kf7 {[%clk 0:00:25.9]} 41. Kc1 {[%clk 0:03:43.8]} 41... Ke6 {[%clk 0:00:04.9]} 42. Kb2 {[%clk 0:01:52.2]} 42... Bh3 {[%clk 0:05:40.1]} 43. a4 {[%clk 0:05:15.7]} 43... Kd7 {[%clk 0:10:12.1]} 44. Ka3 {[%clk 0:01:06.2]} 44... Kc6 {[%clk 0:03:15]} 45. Be3 {[%clk 0:03:19.7]} 45... bxa4 {[%clk 1:16:34.4]} 46. Kxa4 {[%clk 0:00:03.6]} 46... Kd5 {[%clk 0:02:04.6]} 47. Ka5 {[%clk 0:10:51.4]} 47... Ke4 {[%clk 0:00:38.6]} 48. Bd2 {[%clk 0:10:24.2]} 48... Kd3 {[%clk 0:00:03.7]} 49. Be1 {[%clk 0:07:57.8]} 49... Ke2 {[%clk 0:00:09.6]} 50. Bg3 {[%clk 0:52:34.4]} 50... Kd3 {[%clk 0:35:20.8]} 51. Be5 {[%clk 0:21:46.8]} 51... Ke4 {[%clk 0:09:14.4]} 52. Bf6 {[%clk 0:01:16.8]} 52... Kf5 {[%clk 0:31:52.3]} 53. Kxa6 {[%clk 0:03:11.1]} 53... Ke6 {[%clk 0:09:39.8]} 1-0\n","time_control":"1/172800","end_time":1659222345,"rated":false,"tcn":"kA!TlB0Sbs2UcM92mCZRgv8?ft98eh3VMF5ZCKRKBKZKvK7BKvBPdkTNabNDFwDtktSKsJPRvBYQbeQJBHRzHYJAtszsjs6LY4Lt4Y80YJ0ZwKZJK2tf2VfmnvJdgndenemtelXHiqWOVu1LoELEvE!2EMtLuP21lc1ScjLxqySZjqZQPuHyqyQJyGJCulCtletmewmtwKtCKTCLGOLS","uuid":"676231ea-0a26-11ed-811f-1ada6401000b","initial_setup":"rnbqkbnr/pppppppp/8/8/8/8/PPPPPPPP/RNBQKBNR w KQkq - 0 1","fen":"8/8/K3kBp1/6P1/2p5/2P4b/7P/8 w - - 1 54","start_time":1658539557,"time_class":"daily","rules":"chess","white":{"rating":1355,"result":"win","@id":"https://api.chess.com/pub/player/whyterabbittt","username":"WhyteRabbittt","uuid":"b0d2104a-650b-11e7-801c-000000000000"},"black":{"rating":1685,"result":"resigned","@id":"https://api.chess.com/pub/player/ozzytor","username":"OzzyTor","uuid":"bae28030-220b-11e7-8008-000000000000"},"eco":"https://www.chess.com/openings/Indian-Game-East-Indian-Defense-3.Nc3"}]}